stopwatch.py
stopwatch_global.py
dbx_stopwatch-1.6.dist-info/METADATA
dbx_stopwatch-1.6.dist-info/RECORD
dbx_stopwatch-1.6.dist-info/WHEEL
dbx_stopwatch-1.6.dist-info/top_level.txt
