Metadata-Version: 2.1
Name: dbx-stopwatch
Version: 1.6
Summary: Scoped, nested, aggregated python timing library
Home-page: https://github.com/dropbox/stopwatch
Author: Nipunn Koorapati
Author-email: nipunn@dropbox.com
License: Apache License 2.0
Download-URL: https://github.com/dropbox/stopwatch/tarball/1.6
Keywords: stopwatch dropbox
Platform: UNKNOWN
